MANIFEST.in
README.md
pyproject.toml
requirements.txt
setup.cfg
setup.py
venvhpl/__init__.py
venvhpl/venvhpl.py
venvhpl.egg-info/PKG-INFO
venvhpl.egg-info/SOURCES.txt
venvhpl.egg-info/dependency_links.txt
venvhpl.egg-info/entry_points.txt
venvhpl.egg-info/top_level.txt