Metadata-Version: 2.1
Name: venvhpl
Version: 1.0.0
Summary: Links Host's Python Library into Virtualenv
Home-page: https://github.com/mcfletch/venvhpl
Author: Mike C. Fletcher
Author-email: mcfletch@vrplumber.com
License: MIT
Download-URL: https://github.com/mcfletch/venvhpl/tarball/1.0.0
Keywords: venv host package link
Platform: UNKNOWN
Classifier: Intended Audience :: Developers
Classifier: Programming Language :: Python :: 3
Classifier: Programming Language :: Python :: 2
